<?xml version="1.0" encoding="utf-8" ?>
<c2eventsheet>
    <!--All the 'name' attributes are ignored by Construct 2 - they are there for readability only.-->
    <name>Quarto5 Event</name>
    <events>
        <variable constant="0" name="Quarto5_Rooms" sid="604301834109449" static="0" type="number">0</variable>
        <event-group description="" sid="633863165396450" title="Movimento DonQuarto5">
            <sub-events>
                <event-block sid="627479070877830">
                    <conditions>
                        <condition behavior="8Direction" id="0" inverted="1" name="Is moving" sid="630229083030792" type="Plataforma" />
                        <condition id="-7" name="Compare instance variable" sid="370896569866696" type="DonFrey">
                            <param id="0" name="Instance variable">Direção</param>
                            <param id="1" name="Comparison">0</param>
                            <param id="2" name="Value">1</param>
                        </condition>
                    </conditions>
                    <actions>
                        <action id="4" name="Set animation" sid="953589014614813" type="DonFrey">
                            <param id="0" name="Animation">&quot;parado_esquerda&quot;</param>
                            <param id="1" name="From">1</param>
                        </action>
                    </actions>
                </event-block>
                <event-block sid="947220428269436">
                    <conditions>
                        <condition behavior="8Direction" id="0" inverted="1" name="Is moving" sid="690309763472471" type="Plataforma" />
                        <condition id="-7" name="Compare instance variable" sid="768057133100543" type="DonFrey">
                            <param id="0" name="Instance variable">Direção</param>
                            <param id="1" name="Comparison">0</param>
                            <param id="2" name="Value">2</param>
                        </condition>
                    </conditions>
                    <actions>
                        <action id="4" name="Set animation" sid="588362162008778" type="DonFrey">
                            <param id="0" name="Animation">&quot;parado_direita&quot;</param>
                            <param id="1" name="From">1</param>
                        </action>
                    </actions>
                </event-block>
                <event-block sid="755688038764851">
                    <conditions>
                        <condition behavior="8Direction" id="0" inverted="1" name="Is moving" sid="298517274646529" type="Plataforma" />
                        <condition id="-7" name="Compare instance variable" sid="934387690326637" type="DonFrey">
                            <param id="0" name="Instance variable">Direção</param>
                            <param id="1" name="Comparison">0</param>
                            <param id="2" name="Value">3</param>
                        </condition>
                    </conditions>
                    <actions>
                        <action id="4" name="Set animation" sid="684436755068318" type="DonFrey">
                            <param id="0" name="Animation">&quot;parado_cima&quot;</param>
                            <param id="1" name="From">1</param>
                        </action>
                    </actions>
                </event-block>
                <event-block sid="719762935484402">
                    <conditions>
                        <condition behavior="8Direction" id="0" inverted="1" name="Is moving" sid="753392483143316" type="Plataforma" />
                        <condition id="-7" name="Compare instance variable" sid="529826260618581" type="DonFrey">
                            <param id="0" name="Instance variable">Direção</param>
                            <param id="1" name="Comparison">0</param>
                            <param id="2" name="Value">4</param>
                        </condition>
                    </conditions>
                    <actions>
                        <action id="4" name="Set animation" sid="648636425917902" type="DonFrey">
                            <param id="0" name="Animation">&quot;parado_baixo&quot;</param>
                            <param id="1" name="From">1</param>
                        </action>
                    </actions>
                </event-block>
                <event-block sid="158533108936017">
                    <conditions>
                        <condition id="4" name="Is touching object" sid="475029507114356" type="Touch">
                            <param id="0" name="Object">SetaE</param>
                        </condition>
                        <condition id="4" inverted="1" name="Is touching object" sid="267887243100503" type="Touch">
                            <param id="0" name="Object">SetaD</param>
                        </condition>
                        <condition id="4" inverted="1" name="Is touching object" sid="638637670802163" type="Touch">
                            <param id="0" name="Object">SetaC</param>
                        </condition>
                        <condition id="4" inverted="1" name="Is touching object" sid="171877550092397" type="Touch">
                            <param id="0" name="Object">SetaB</param>
                        </condition>
                    </conditions>
                    <actions>
                        <action behavior="8Direction" id="7" name="Simulate control" sid="799352808149627" type="Plataforma">
                            <param id="0" name="Control">0</param>
                        </action>
                        <action id="4" name="Set animation" sid="213719979973912" type="DonFrey">
                            <param id="0" name="Animation">&quot;esquerda&quot;</param>
                            <param id="1" name="From">1</param>
                        </action>
                        <action id="-10" name="Set value" sid="756954577760573" type="DonFrey">
                            <param id="0" name="Instance variable">Direção</param>
                            <param id="1" name="Value">1</param>
                        </action>
                    </actions>
                </event-block>
                <event-block sid="402594012351475">
                    <conditions>
                        <condition id="4" name="Is touching object" sid="476048177853806" type="Touch">
                            <param id="0" name="Object">SetaE</param>
                        </condition>
                        <condition id="4" inverted="1" name="Is touching object" sid="418281941707871" type="Touch">
                            <param id="0" name="Object">SetaD</param>
                        </condition>
                        <condition id="4" name="Is touching object" sid="464298546816642" type="Touch">
                            <param id="0" name="Object">SetaC</param>
                        </condition>
                        <condition id="4" inverted="1" name="Is touching object" sid="110569173592206" type="Touch">
                            <param id="0" name="Object">SetaB</param>
                        </condition>
                    </conditions>
                    <actions>
                        <action behavior="8Direction" id="7" name="Simulate control" sid="637910398626885" type="Plataforma">
                            <param id="0" name="Control">0</param>
                        </action>
                        <action behavior="8Direction" id="7" name="Simulate control" sid="396979934894697" type="Plataforma">
                            <param id="0" name="Control">2</param>
                        </action>
                        <action id="4" name="Set animation" sid="927747917537011" type="DonFrey">
                            <param id="0" name="Animation">&quot;esquerda&quot;</param>
                            <param id="1" name="From">1</param>
                        </action>
                        <action id="-10" name="Set value" sid="788776393711046" type="DonFrey">
                            <param id="0" name="Instance variable">Direção</param>
                            <param id="1" name="Value">1</param>
                        </action>
                    </actions>
                </event-block>
                <event-block sid="561214037842877">
                    <conditions>
                        <condition id="4" name="Is touching object" sid="888452443135861" type="Touch">
                            <param id="0" name="Object">SetaE</param>
                        </condition>
                        <condition id="4" name="Is touching object" sid="565435583864057" type="Touch">
                            <param id="0" name="Object">SetaD</param>
                        </condition>
                        <condition id="4" inverted="1" name="Is touching object" sid="524993967668758" type="Touch">
                            <param id="0" name="Object">SetaC</param>
                        </condition>
                        <condition id="4" inverted="1" name="Is touching object" sid="437453500284012" type="Touch">
                            <param id="0" name="Object">SetaB</param>
                        </condition>
                    </conditions>
                    <actions>
                        <action behavior="8Direction" id="7" name="Simulate control" sid="252002464672398" type="Plataforma">
                            <param id="0" name="Control">0</param>
                        </action>
                        <action behavior="8Direction" id="7" name="Simulate control" sid="246832218936161" type="Plataforma">
                            <param id="0" name="Control">3</param>
                        </action>
                        <action id="4" name="Set animation" sid="564686311656413" type="DonFrey">
                            <param id="0" name="Animation">&quot;esquerda&quot;</param>
                            <param id="1" name="From">1</param>
                        </action>
                        <action id="-10" name="Set value" sid="264461222237320" type="DonFrey">
                            <param id="0" name="Instance variable">Direção</param>
                            <param id="1" name="Value">1</param>
                        </action>
                    </actions>
                </event-block>
                <event-block sid="183514612009443">
                    <conditions>
                        <condition id="4" inverted="1" name="Is touching object" sid="431186359118914" type="Touch">
                            <param id="0" name="Object">SetaE</param>
                        </condition>
                        <condition id="4" name="Is touching object" sid="294479244864607" type="Touch">
                            <param id="0" name="Object">SetaD</param>
                        </condition>
                        <condition id="4" inverted="1" name="Is touching object" sid="730687234348447" type="Touch">
                            <param id="0" name="Object">SetaC</param>
                        </condition>
                        <condition id="4" inverted="1" name="Is touching object" sid="547635365632471" type="Touch">
                            <param id="0" name="Object">SetaB</param>
                        </condition>
                    </conditions>
                    <actions>
                        <action behavior="8Direction" id="7" name="Simulate control" sid="253532957616010" type="Plataforma">
                            <param id="0" name="Control">1</param>
                        </action>
                        <action id="4" name="Set animation" sid="247529009504696" type="DonFrey">
                            <param id="0" name="Animation">&quot;direita&quot;</param>
                            <param id="1" name="From">1</param>
                        </action>
                        <action id="-10" name="Set value" sid="251791574726793" type="DonFrey">
                            <param id="0" name="Instance variable">Direção</param>
                            <param id="1" name="Value">2</param>
                        </action>
                    </actions>
                </event-block>
                <event-block sid="142358444915894">
                    <conditions>
                        <condition id="4" inverted="1" name="Is touching object" sid="749625213863482" type="Touch">
                            <param id="0" name="Object">SetaE</param>
                        </condition>
                        <condition id="4" name="Is touching object" sid="577841931307104" type="Touch">
                            <param id="0" name="Object">SetaD</param>
                        </condition>
                        <condition id="4" name="Is touching object" sid="988813753715850" type="Touch">
                            <param id="0" name="Object">SetaC</param>
                        </condition>
                        <condition id="4" inverted="1" name="Is touching object" sid="139373794990213" type="Touch">
                            <param id="0" name="Object">SetaB</param>
                        </condition>
                    </conditions>
                    <actions>
                        <action behavior="8Direction" id="7" name="Simulate control" sid="384515529459153" type="Plataforma">
                            <param id="0" name="Control">1</param>
                        </action>
                        <action behavior="8Direction" id="7" name="Simulate control" sid="784773421173434" type="Plataforma">
                            <param id="0" name="Control">2</param>
                        </action>
                        <action id="4" name="Set animation" sid="740624950488024" type="DonFrey">
                            <param id="0" name="Animation">&quot;direita&quot;</param>
                            <param id="1" name="From">1</param>
                        </action>
                        <action id="-10" name="Set value" sid="114638336188406" type="DonFrey">
                            <param id="0" name="Instance variable">Direção</param>
                            <param id="1" name="Value">2</param>
                        </action>
                    </actions>
                </event-block>
                <event-block sid="855940142202976">
                    <conditions>
                        <condition id="4" inverted="1" name="Is touching object" sid="453375493312011" type="Touch">
                            <param id="0" name="Object">SetaE</param>
                        </condition>
                        <condition id="4" name="Is touching object" sid="314030287858718" type="Touch">
                            <param id="0" name="Object">SetaD</param>
                        </condition>
                        <condition id="4" inverted="1" name="Is touching object" sid="496261648595136" type="Touch">
                            <param id="0" name="Object">SetaC</param>
                        </condition>
                        <condition id="4" name="Is touching object" sid="581069131384537" type="Touch">
                            <param id="0" name="Object">SetaB</param>
                        </condition>
                    </conditions>
                    <actions>
                        <action behavior="8Direction" id="7" name="Simulate control" sid="219719237411562" type="Plataforma">
                            <param id="0" name="Control">1</param>
                        </action>
                        <action behavior="8Direction" id="7" name="Simulate control" sid="920038661370255" type="Plataforma">
                            <param id="0" name="Control">3</param>
                        </action>
                        <action id="4" name="Set animation" sid="237342204213557" type="DonFrey">
                            <param id="0" name="Animation">&quot;direita&quot;</param>
                            <param id="1" name="From">1</param>
                        </action>
                        <action id="-10" name="Set value" sid="996384566300300" type="DonFrey">
                            <param id="0" name="Instance variable">Direção</param>
                            <param id="1" name="Value">2</param>
                        </action>
                    </actions>
                </event-block>
                <event-block sid="708543618441104">
                    <conditions>
                        <condition id="4" inverted="1" name="Is touching object" sid="233055960568631" type="Touch">
                            <param id="0" name="Object">SetaE</param>
                        </condition>
                        <condition id="4" inverted="1" name="Is touching object" sid="596506621321578" type="Touch">
                            <param id="0" name="Object">SetaD</param>
                        </condition>
                        <condition id="4" name="Is touching object" sid="606790677560348" type="Touch">
                            <param id="0" name="Object">SetaC</param>
                        </condition>
                        <condition id="4" inverted="1" name="Is touching object" sid="467974692313964" type="Touch">
                            <param id="0" name="Object">SetaB</param>
                        </condition>
                    </conditions>
                    <actions>
                        <action behavior="8Direction" id="7" name="Simulate control" sid="974334830160777" type="Plataforma">
                            <param id="0" name="Control">2</param>
                        </action>
                        <action id="4" name="Set animation" sid="632462611109447" type="DonFrey">
                            <param id="0" name="Animation">&quot;cima&quot;</param>
                            <param id="1" name="From">1</param>
                        </action>
                        <action id="-10" name="Set value" sid="978800003377669" type="DonFrey">
                            <param id="0" name="Instance variable">Direção</param>
                            <param id="1" name="Value">3</param>
                        </action>
                    </actions>
                </event-block>
                <event-block sid="592062880999616">
                    <conditions>
                        <condition id="4" inverted="1" name="Is touching object" sid="339239680364875" type="Touch">
                            <param id="0" name="Object">SetaE</param>
                        </condition>
                        <condition id="4" inverted="1" name="Is touching object" sid="566164420876313" type="Touch">
                            <param id="0" name="Object">SetaD</param>
                        </condition>
                        <condition id="4" inverted="1" name="Is touching object" sid="994735856713475" type="Touch">
                            <param id="0" name="Object">SetaC</param>
                        </condition>
                        <condition id="4" name="Is touching object" sid="370312195119902" type="Touch">
                            <param id="0" name="Object">SetaB</param>
                        </condition>
                    </conditions>
                    <actions>
                        <action behavior="8Direction" id="7" name="Simulate control" sid="532511654555359" type="Plataforma">
                            <param id="0" name="Control">3</param>
                        </action>
                        <action id="4" name="Set animation" sid="589323550601604" type="DonFrey">
                            <param id="0" name="Animation">&quot;baixo&quot;</param>
                            <param id="1" name="From">1</param>
                        </action>
                        <action id="-10" name="Set value" sid="948050176321095" type="DonFrey">
                            <param id="0" name="Instance variable">Direção</param>
                            <param id="1" name="Value">4</param>
                        </action>
                    </actions>
                </event-block>
                <event-block sid="722863916128036">
                    <conditions>
                        <condition id="-2" name="On start of layout" sid="550820206284045" type="System" />
                    </conditions>
                    <actions>
                        <action behavior="Pin" id="0" name="Pin to object" sid="492883182187945" type="DonFrey">
                            <param id="0" name="Pin to">Plataforma</param>
                            <param id="1" name="Mode">0</param>
                        </action>
                    </actions>
                </event-block>
            </sub-events>
        </event-group>
        <event-block sid="676999742222563">
            <conditions>
                <condition id="1" name="Is overlapping another object" sid="263130720885336" type="DonFrey">
                    <param id="0" name="Object">5_torooms</param>
                </condition>
                <condition id="4" name="Is touching object" sid="335533079565609" type="Touch">
                    <param id="0" name="Object">SetaBotao</param>
                </condition>
            </conditions>
            <actions>
                <action id="-12" name="Set group active" sid="126610559546654" type="System">
                    <param id="0" name="Group name">&quot;Movimento Don&quot;</param>
                    <param id="1" name="State">0</param>
                </action>
                <action behavior="8Direction" id="8" name="Set enabled" sid="304811313309804" type="Plataforma">
                    <param id="0" name="State">0</param>
                </action>
                <action id="-16" name="Wait" sid="198166177659465" type="System">
                    <param id="0" name="Seconds">0.5</param>
                </action>
                <action id="-2" name="Go to layout" sid="712943925569828" type="System">
                    <param id="0" name="Layout">Rooms</param>
                </action>
                <action id="-9" name="Set value" sid="451967345804010" type="System">
                    <param id="0" name="Variable">Quarto5_Rooms</param>
                    <param id="1" name="Value">1</param>
                </action>
                <action behavior="8Direction" id="8" name="Set enabled" sid="177970350180099" type="Plataforma">
                    <param id="0" name="State">1</param>
                </action>
            </actions>
        </event-block>
        <event-block sid="809046091559495">
            <conditions>
                <condition id="1" name="Is overlapping another object" sid="678137781991251" type="DonFrey">
                    <param id="0" name="Object">Chest5_Room5</param>
                </condition>
                <condition id="-7" name="Compare instance variable" sid="339552636288993" type="Chest5_Room5">
                    <param id="0" name="Instance variable">Acessado</param>
                    <param id="1" name="Comparison">0</param>
                    <param id="2" name="Value">0</param>
                </condition>
                <condition id="4" name="Is touching object" sid="478683123492611" type="Touch">
                    <param id="0" name="Object">SetaBotao</param>
                </condition>
            </conditions>
            <actions>
                <action id="0" name="Play" sid="820996319228773" type="Audio">
                    <param id="0" name="Audio file">OpenDoor</param>
                    <param id="2" name="Loop">0</param>
                    <param id="3" name="Volume">0</param>
                    <param id="1" name="Tag (optional)">&quot;&quot;</param>
                </action>
                <action id="-12" name="Set group active" sid="124898240099885" type="System">
                    <param id="0" name="Group name">&quot;Movimento Don&quot;</param>
                    <param id="1" name="State">0</param>
                </action>
                <action behavior="8Direction" id="8" name="Set enabled" sid="894232148341012" type="Plataforma">
                    <param id="0" name="State">0</param>
                </action>
                <action id="4" name="Set animation" sid="608290970169241" type="Chest5_Room5">
                    <param id="0" name="Animation">&quot;Open&quot;</param>
                    <param id="1" name="From">1</param>
                </action>
                <action id="-9" name="Set value" sid="323673262252443" type="System">
                    <param id="0" name="Variable">Key5_5to1</param>
                    <param id="1" name="Value">1</param>
                </action>
                <action id="-16" name="Wait" sid="382910983210067" type="System">
                    <param id="0" name="Seconds">0.5</param>
                </action>
                <action id="-3" name="Set position" sid="165665295771786" type="Note5_5to1">
                    <param id="0" name="X">426</param>
                    <param id="1" name="Y">599.172</param>
                </action>
                <action id="-10" name="Set value" sid="241412559227350" type="Chest5_Room5">
                    <param id="0" name="Instance variable">Acessado</param>
                    <param id="1" name="Value">1</param>
                </action>
            </actions>
        </event-block>
        <event-block sid="356712132840495">
            <conditions>
                <condition id="4" name="Is touching object" sid="230830319162777" type="Touch">
                    <param id="0" name="Object">SetaBotao</param>
                </condition>
            </conditions>
            <actions>
                <action id="-3" name="Set position" sid="979947815129507" type="Note5_5to1">
                    <param id="0" name="X">-514</param>
                    <param id="1" name="Y">541</param>
                </action>
                <action behavior="8Direction" id="8" name="Set enabled" sid="228663532729054" type="Plataforma">
                    <param id="0" name="State">1</param>
                </action>
                <action id="-12" name="Set group active" sid="252851880582170" type="System">
                    <param id="0" name="Group name">&quot;Movimento Don&quot;</param>
                    <param id="1" name="State">1</param>
                </action>
            </actions>
        </event-block>
        <event-block sid="211829082658425">
            <conditions>
                <condition id="-2" name="On start of layout" sid="805944066113416" type="System" />
            </conditions>
            <actions>
                <action id="33" name="Stop all" sid="667642897829837" type="Audio" />
                <action id="0" name="Play" sid="326415184870696" type="Audio">
                    <param id="0" name="Audio file">The_Eagles_-_Wasted_Time</param>
                    <param id="2" name="Loop">1</param>
                    <param id="3" name="Volume">0</param>
                    <param id="1" name="Tag (optional)">&quot;&quot;</param>
                </action>
            </actions>
        </event-block>
    </events>
</c2eventsheet>
